mypywallpaper/__init__.py
mypywallpaper-0.1.0.dist-info/LICENSE
mypywallpaper-0.1.0.dist-info/METADATA
mypywallpaper-0.1.0.dist-info/WHEEL
mypywallpaper-0.1.0.dist-info/RECORD
