Metadata-Version: 2.3
Name: mypywallpaper
Version: 0.1.0
Summary: 
License: MIT License
Author: tct123
Author-email: 42028373+tct123@users.noreply.github.com
Requires-Python: >=3.13
Classifier: License :: Other/Proprietary License
Classifier: Programming Language :: Python :: 3
Classifier: Programming Language :: Python :: 3.13
